dynamodb_autoincrement.py
dynamodb_autoincrement-0.2.0.dist-info/LICENSE.txt
dynamodb_autoincrement-0.2.0.dist-info/METADATA
dynamodb_autoincrement-0.2.0.dist-info/WHEEL
dynamodb_autoincrement-0.2.0.dist-info/top_level.txt
dynamodb_autoincrement-0.2.0.dist-info/RECORD
