Metadata-Version: 2.1
Name: dynamodb-autoincrement
Version: 0.2.0
Summary: Use optimistic locking to put DynamoDB records with auto-incrementing attributes. Python port of https://github.com/nasa-gcn/dynamodb-autoincrement
Author-email: Leo Singer <leo.p.singer@nasa.gov>
License: Apache-2.0
Project-URL: source, https://github.com/nasa-gcn/python-dynamodb-autoincrement
Classifier: Intended Audience :: Developers
Classifier: Intended Audience :: Information Technology
Classifier: Topic :: Database
Requires-Python: >=3.9
License-File: LICENSE.txt
Requires-Dist: aioboto3
Requires-Dist: boto3-missing
Requires-Dist: types-aioboto3[dynamodb]
Provides-Extra: test
Requires-Dist: pytest ; extra == 'test'
Requires-Dist: pytest-asyncio ; extra == 'test'
Requires-Dist: pytest-dynamodb ; extra == 'test'
